{
	"name": "objSlowDown",
	"plugin-id": "Sprite",
	"sid": 793423960496628,
	"isGlobal": false,
	"editorNewInstanceIsReplica": true,
	"instanceVariables": [
		{
			"name": "slowBy",
			"type": "number",
			"desc": "",
			"show": true,
			"sid": 927026666980149
		}
	],
	"behaviorTypes": [],
	"effectTypes": [],
	"animations": {
		"items": [
			{
				"frames": [
					{
						"width": 288,
						"height": 288,
						"originX": 0,
						"originY": 0,
						"originalSource": "",
						"exportFormat": "lossless",
						"exportQuality": 0.8,
						"fileType": "image/png",
						"imageSpriteId": 4187753,
						"useCollisionPoly": true,
						"duration": 1,
						"tag": ""
					}
				],
				"sid": 436835113174643,
				"name": "Animation 1",
				"isLooping": false,
				"isPingPong": false,
				"repeatCount": 1,
				"repeatTo": 0,
				"speed": 5
			}
		],
		"subfolders": []
	}
}